Metadata-Version: 2.1
Name: stampel
Version: 0.1.1
Summary: Commandline tool for quickly entering multiple similar commands.
Home-page: https://github.com/voidcase/stampel
License: MIT
Download-URL: https://github.com/voidcase/stampel/archive/v0.1.1.tar.gz
Keywords: data-entry,utility,commandline
Platform: UNKNOWN
Classifier: Development Status :: 3 - Alpha
Classifier: Programming Language :: Python :: 3
Classifier: License :: OSI Approved :: MIT License
Classifier: Environment :: Console
Classifier: Topic :: Utilities
